AUTHORS.rst
CHANGELOG.rst
LICENSE
MANIFEST.in
README.rst
setup.py
mote/.babelrc
mote/.editorconfig
mote/.eslintrc
mote/.nvmrc
mote/.stylelintrc
mote/__init__.py
mote/__init__.pyc
mote/_config.json
mote/apps.py
mote/apps.pyc
mote/gulpfile.js
mote/models.py
mote/models.pyc
mote/package.json
mote/urls.py
mote/urls.pyc
mote/utils.py
mote/utils.pyc
mote/views.py
mote/views.pyc
mote/webpack.config.js
mote/yarn.lock
mote/__pycache__/__init__.cpython-35.pyc
mote/__pycache__/apps.cpython-35.pyc
mote/__pycache__/models.cpython-35.pyc
mote/__pycache__/urls.cpython-35.pyc
mote/__pycache__/utils.cpython-35.pyc
mote/__pycache__/views.cpython-35.pyc
mote/api/__init__.py
mote/api/__init__.pyc
mote/api/__pycache__/__init__.cpython-35.pyc
mote/build-helpers/webpack/helpers.js
mote/loaders/__init__.py
mote/loaders/__init__.pyc
mote/loaders/app_directories.py
mote/loaders/app_directories.pyc
mote/loaders/__pycache__/__init__.cpython-35.pyc
mote/loaders/__pycache__/app_directories.cpython-35.pyc
mote/mui-source/projects/mui/website/src/main.js
mote/mui-source/projects/mui/website/src/styles.scss
mote/mui-source/projects/mui/website/src/app/documentation-toggler.js
mote/mui-source/projects/mui/website/src/app/variation-toggler.js
mote/mui-source/projects/mui/website/src/app/helpers/document-ready.js
mote/mui-source/projects/mui/website/src/config/_config.scss
mote/mui-source/projects/mui/website/src/config/_pattern-presets.scss
mote/mui-source/projects/mui/website/src/patterns/atoms/color-swatch/_color-swatch.scss
mote/mui-source/projects/mui/website/src/patterns/atoms/color-swatch/color-swatch.html
mote/mui-source/projects/mui/website/src/patterns/atoms/color-swatch/index.html
mote/mui-source/projects/mui/website/src/patterns/atoms/content-area/_content-area.scss
mote/mui-source/projects/mui/website/src/patterns/atoms/content-area/index.html
mote/mui-source/projects/mui/website/src/patterns/atoms/logo/_logo.scss
mote/mui-source/projects/mui/website/src/patterns/atoms/logo/index.html
mote_prk.egg-info/PKG-INFO
mote_prk.egg-info/SOURCES.txt
mote_prk.egg-info/dependency_links.txt
mote_prk.egg-info/requires.txt
mote_prk.egg-info/top_level.txt
mote_prk.egg-info/zip-safe